experiments/fpga/phase1/updown.synth.v
/* Generated by Yosys 0.33 (git sha1 2584903a060) */

module updown(clk, rst, en, load, updn, din, q);
  wire [3:0] _00_;
  wire [3:0] _01_;
  wire [3:0] _02_;
  wire [3:0] _03_;
  wire [3:0] _04_;
  wire _05_;
  wire _06_;
  input clk;
  wire clk;
  input [3:0] din;
  wire [3:0] din;
  input en;
  wire en;
  input load;
  wire load;
  wire [3:0] nextq;
  output [3:0] q;
  reg [3:0] q;
  input rst;
  wire rst;
  wire [3:0] step;
  input updn;
  wire updn;
  always @(posedge clk)
    if (rst) q[0] <= 1'h0;
    else if (en) q[0] <= nextq[0];
  always @(posedge clk)
    if (rst) q[1] <= 1'h0;
    else if (en) q[1] <= nextq[1];
  always @(posedge clk)
    if (rst) q[2] <= 1'h0;
    else if (en) q[2] <= nextq[2];
  always @(posedge clk)
    if (rst) q[3] <= 1'h0;
    else if (en) q[3] <= nextq[3];
  assign step[0] = ~q[0];
  assign _03_[3] = ~q[3];
  assign _03_[2] = ~q[2];
  assign step[3] = updn ? _01_[3] : _04_[3];
  assign nextq[0] = load ? din[0] : step[0];
  assign nextq[1] = load ? din[1] : step[1];
  assign nextq[2] = load ? din[2] : step[2];
  assign nextq[3] = load ? din[3] : step[3];
  assign step[1] = updn ? _01_[1] : _04_[1];
  assign step[2] = updn ? _01_[2] : _04_[2];
  assign _03_[1] = ~q[1];
  assign _01_[1] = q[1] ^ q[0];
  assign _01_[2] = q[2] ^ _00_[1];
  assign _01_[3] = q[3] ^ _00_[2];
  assign _04_[1] = _03_[1] ^ q[0];
  assign _04_[2] = _03_[2] ^ _02_[1];
  assign _04_[3] = _03_[3] ^ _02_[2];
  assign _00_[1] = q[1] & q[0];
  assign _00_[2] = q[2] & _00_[1];
  assign _05_ = _03_[1] & q[0];
  assign _06_ = _03_[2] & _02_[1];
  assign _02_[1] = q[1] | _05_;
  assign _02_[2] = q[2] | _06_;
  assign _00_[0] = q[0];
  assign _01_[0] = step[0];
  assign _02_[0] = q[0];
  assign _03_[0] = q[0];
  assign _04_[0] = step[0];
endmodule

experiments/fpga/phase1/updown_tb.v
// updown_tb.v - reference testbench / oracle generator for updown.v
//
// Drives one reset rising edge, then a scripted sequence of rising edges that
// exercises load, count-up, count-down, enable-hold, and wrap-around.  On every
// COUNTED rising edge it samples q (the value AFTER that edge) and prints exactly
// one line:
//     cycle <n> q=<decimal>
// to stdout (redirected into updown.ref.trace), and dumps a VCD.
//
// Cycle numbering convention (mirrors phase0/counter_tb.v):
//   * The reset edge is NOT counted/printed.
//   * cycle 0 is the first post-reset counted edge; q is sampled AFTER the edge.
//
// Stimulus script (control values are set on the negedge BEFORE each counted
// rising edge so they are stable at the edge -- the same discipline phase0 uses
// for releasing reset).  The exact schedule is reproduced bit-for-bit by the
// interpreter test (tests/test_fpga2.tcl).
`timescale 1ns/1ps
module updown_tb;
    reg        clk  = 1'b0;
    reg        rst  = 1'b1;
    reg        en   = 1'b0;
    reg        load = 1'b0;
    reg        updn = 1'b1;
    reg  [3:0] din  = 4'd0;
    wire [3:0] q;
    integer    cyc;

    updown dut (.clk(clk), .rst(rst), .en(en), .load(load),
                .updn(updn), .din(din), .q(q));

    // The per-cycle control schedule, applied on the negedge before each counted
    // rising edge.  {en, load, updn, din} for cycles 0..19.  Chosen to walk
    // through: load 10, count up (wrap 15->0), hold, count down (wrap 0->15),
    // and a reload.
    // cyc: en load updn din   effect
    //   0:  1   1    1    10   load 10
    //   1:  1   0    1    -    11
    //   2:  1   0    1    -    12
    //   3:  1   0    1    -    13
    //   4:  1   0    1    -    14
    //   5:  1   0    1    -    15
    //   6:  1   0    1    -    0   (wrap up)
    //   7:  0   0    1    -    0   (disabled -> hold)
    //   8:  1   0    0    -    15  (wrap down)
    //   9:  1   0    0    -    14
    //  10:  1   0    0    -    13
    //  11:  1   1    0    3    load 3
    //  12:  1   0    0    -    2
    //  13:  1   0    0    -    1
    //  14:  1   0    0    -    0
    //  15:  1   0    0    -    15  (wrap down)
    //  16:  0   1    1    9    disabled -> hold (load ignored)
    //  17:  1   0    1    -    0   (15 up -> wrap)
    //  18:  1   0    1    -    1
    //  19:  1   1    1    7    load 7
    reg [9:0] script [0:19];
    initial begin
        // pack {en[9], load[8], updn[7], din[3:0] padded to 8} -> use fields:
        // we encode as {en, load, updn, din[3:0]} = 7 bits, low to high din.
        script[0]  = {1'b1,1'b1,1'b1,4'd10};
        script[1]  = {1'b1,1'b0,1'b1,4'd0};
        script[2]  = {1'b1,1'b0,1'b1,4'd0};
        script[3]  = {1'b1,1'b0,1'b1,4'd0};
        script[4]  = {1'b1,1'b0,1'b1,4'd0};
        script[5]  = {1'b1,1'b0,1'b1,4'd0};
        script[6]  = {1'b1,1'b0,1'b1,4'd0};
        script[7]  = {1'b0,1'b0,1'b1,4'd0};
        script[8]  = {1'b1,1'b0,1'b0,4'd0};
        script[9]  = {1'b1,1'b0,1'b0,4'd0};
        script[10] = {1'b1,1'b0,1'b0,4'd0};
        script[11] = {1'b1,1'b1,1'b0,4'd3};
        script[12] = {1'b1,1'b0,1'b0,4'd0};
        script[13] = {1'b1,1'b0,1'b0,4'd0};
        script[14] = {1'b1,1'b0,1'b0,4'd0};
        script[15] = {1'b1,1'b0,1'b0,4'd0};
        script[16] = {1'b0,1'b1,1'b1,4'd9};
        script[17] = {1'b1,1'b0,1'b1,4'd0};
        script[18] = {1'b1,1'b0,1'b1,4'd0};
        script[19] = {1'b1,1'b1,1'b1,4'd7};
    end

    initial begin
        $dumpfile("updown.ref.vcd");
        $dumpvars(0, updown_tb);

        // Hold reset across one full clock so the reset edge clears q.
        @(posedge clk);          // reset rising edge: q <= 0
        @(negedge clk);
        rst = 1'b0;              // release reset before the next rising edge

        for (cyc = 0; cyc < 20; cyc = cyc + 1) begin
            // Apply this cycle's controls while clk is low (stable at the edge).
            en   = script[cyc][6];
            load = script[cyc][5];
            updn = script[cyc][4];
            din  = script[cyc][3:0];
            @(posedge clk);      // counting edge
            #1;                  // settle nonblocking update before sampling
            $display("cycle %0d q=%0d", cyc, q);
            @(negedge clk);
        end
        $finish;
    end

    // free-running clock, 10ns period
    always #5 clk = ~clk;
endmodule

fpga/experiments/phase1/updown.ref.vcd
$date
	Wed Jun  3 19:08:58 2026
$end
$version
	Icarus Verilog
$end
$timescale
	1ps
$end
$scope module updown_tb $end
$var wire 4 ! q [3:0] $end
$var reg 1 " clk $end
$var reg 4 # din [3:0] $end
$var reg 1 $ en $end
$var reg 1 % load $end
$var reg 1 & rst $end
$var reg 1 ' updn $end
$var integer 32 ( cyc [31:0] $end
$scope module dut $end
$var wire 1 ) _05_ $end
$var wire 1 * _06_ $end
$var wire 1 " clk $end
$var wire 4 + din [3:0] $end
$var wire 1 $ en $end
$var wire 1 % load $end
$var wire 1 & rst $end
$var wire 1 ' updn $end
$var wire 4 , step [3:0] $end
$var wire 4 - nextq [3:0] $end
$var wire 4 . _04_ [3:0] $end
$var wire 4 / _03_ [3:0] $end
$var wire 4 0 _02_ [3:0] $end
$var wire 4 1 _01_ [3:0] $end
$var wire 4 2 _00_ [3:0] $end
$var reg 4 3 q [3:0] $end
$upscope $end
$upscope $end
$enddefinitions $end
$comment Show the parameter values. $end
$dumpall
$end
#0
$dumpvars
bx 3
bzxxx 2
bx 1
bzxxx 0
bx /
bx .
bx -
bx ,
b0 +
x*
x)
bx (
1'
1&
0%
0$
b0 #
0"
bx !
$end
#5000
0*
b1 -
b1111 .
b1 ,
0)
b1 1
bz000 2
bz000 0
b1110 /
b0 !
b0 3
1"
#10000
b1010 -
b1010 #
b1010 +
1%
1$
b0 (
0&
0"
#15000
b1011 ,
1*
b1001 .
b100 /
b1011 1
bz110 0
b1010 !
b1010 3
1"
#20000
b1011 -
b0 #
b0 +
0%
b1 (
0"
#25000
b1100 -
b1100 ,
b1100 1
b1010 .
bz011 2
bz111 0
b101 /
b1011 !
b1011 3
1"
#30000
b10 (
0"
#35000
0*
b1101 -
b1101 1
b1101 ,
b1011 .
bz000 2
bz100 0
b10 /
b1100 !
b1100 3
1"
#40000
b11 (
0"
#45000
b1110 -
b1110 ,
b1110 1
b1100 .
1)
bz001 2
bz111 0
b11 /
b1101 !
b1101 3
1"
#50000
b100 (
0"
#55000
b1111 -
b1111 1
b1111 ,
b1101 .
0)
bz000 2
bz110 0
b0 /
b1110 !
b1110 3
1"
#60000
b101 (
0"
#65000
b0 -
b0 ,
b0 1
b1110 .
bz111 2
bz111 0
b1 /
b1111 !
b1111 3
1"
#70000
b110 (
0"
#75000
b1 -
b1 1
b1 ,
b1111 .
bz000 2
bz000 0
b1110 /
b0 !
b0 3
1"
#80000
0$
b111 (
0"
#85000
1"
#90000
b1111 -
b1111 ,
0'
1$
b1000 (
0"
#95000
b1110 -
b0 1
b1110 ,
b1110 .
0)
bz111 2
bz111 0
b1 /
b1111 !
b1111 3
1"
#100000
b1001 (
0"
#105000
b1101 -
b1101 ,
b1111 1
b1101 .
bz000 2
bz110 0
b0 /
b1110 !
b1110 3
1"
#110000
b1010 (
0"
#115000
1)
b1100 -
b1110 1
b1100 ,
b1100 .
bz001 2
bz111 0
b11 /
b1101 !
b1101 3
1"
#120000
b11 -
b11 #
b11 +
1%
b1011 (
0"
#125000
b10 ,
0)
1*
b10 .
bz011 2
bz111 0
b1101 /
b100 1
b11 !
b11 3
1"
#130000
b10 -
b0 #
b0 +
0%
b1100 (
0"
#135000
b1 -
b1 ,
b11 1
b1 .
bz000 2
bz110 0
b1100 /
b10 !
b10 3
1"
#140000
b1101 (
0"
#145000
b0 -
1)
1*
b10 1
b0 ,
b0 .
bz001 2
bz111 0
b1111 /
b1 !
b1 3
1"
#150000
b1110 (
0"
#155000
0*
b1111 -
b1111 ,
b1 1
b1111 .
0)
bz000 2
bz000 0
b1110 /
b0 !
b0 3
1"
#160000
b1111 (
0"
#165000
b1110 -
b1110 ,
b1110 .
0)
b0 1
bz111 2
bz111 0
b1 /
b1111 !
b1111 3
1"
#170000
b0 ,
b1001 -
b1001 #
b1001 +
1'
1%
0$
b10000 (
0"
#175000
1"
#180000
b0 -
b0 #
b0 +
0%
1$
b10001 (
0"
#185000
b1 -
b1 ,
b1111 .
b1 1
bz000 2
bz000 0
b1110 /
b0 !
b0 3
1"
#190000
b10010 (
0"
#195000
1*
b10 -
b10 ,
b10 1
b0 .
1)
bz001 2
bz111 0
b1111 /
b1 !
b1 3
1"
#200000
b111 -
b111 #
b111 +
1%
b10011 (
0"
#205000
0)
0*
b110 .
b1000 ,
bz111 2
b1001 /
b1000 1
b111 !
b111 3
1"
#210000
b10100 (
0"
