experiments/fpga/phase0/counter.synth.v
/* Generated by Yosys 0.33 (git sha1 2584903a060) */

module counter(clk, rst, q);
  wire [7:0] _00_;
  wire [7:0] _01_;
  wire [7:0] _02_;
  wire _03_;
  wire _04_;
  input clk;
  wire clk;
  output [7:0] q;
  reg [7:0] q;
  input rst;
  wire rst;
  always @(posedge clk)
    if (rst) q[0] <= 1'h0;
    else q[0] <= _01_[0];
  always @(posedge clk)
    if (rst) q[1] <= 1'h0;
    else q[1] <= _02_[1];
  always @(posedge clk)
    if (rst) q[2] <= 1'h0;
    else q[2] <= _02_[2];
  always @(posedge clk)
    if (rst) q[3] <= 1'h0;
    else q[3] <= _02_[3];
  always @(posedge clk)
    if (rst) q[4] <= 1'h0;
    else q[4] <= _02_[4];
  always @(posedge clk)
    if (rst) q[5] <= 1'h0;
    else q[5] <= _02_[5];
  always @(posedge clk)
    if (rst) q[6] <= 1'h0;
    else q[6] <= _02_[6];
  always @(posedge clk)
    if (rst) q[7] <= 1'h0;
    else q[7] <= _02_[7];
  assign _01_[0] = ~q[0];
  assign _02_[1] = q[1] ^ q[0];
  assign _02_[2] = q[2] ^ _00_[1];
  assign _02_[3] = q[3] ^ _00_[2];
  assign _02_[4] = q[4] ^ _00_[3];
  assign _02_[5] = q[5] ^ _00_[4];
  assign _02_[6] = q[6] ^ _00_[5];
  assign _02_[7] = q[7] ^ _00_[6];
  assign _00_[1] = q[1] & q[0];
  assign _00_[3] = _03_ & _00_[1];
  assign _03_ = q[3] & q[2];
  assign _04_ = q[5] & q[4];
  assign _00_[5] = _04_ & _00_[3];
  assign _00_[2] = q[2] & _00_[1];
  assign _00_[4] = q[4] & _00_[3];
  assign _00_[6] = q[6] & _00_[5];
  assign _00_[0] = q[0];
  assign _01_[7:1] = q[7:1];
  assign _02_[0] = _01_[0];
endmodule

fpga/experiments/phase0/counter_tb.v
// counter_tb.v - reference testbench / oracle generator for counter.v
//
// Drives one reset cycle then 40 free-running clock cycles. On every rising
// edge it samples q (the value AFTER that edge) and prints exactly one line:
//     cycle <n> q=<decimal>
// to stdout (redirected into counter.ref.trace), and dumps a VCD.
//
// Cycle numbering convention (see NOTES.md):
//   * The reset edge is NOT counted/printed.
//   * cycle 0 is the first post-reset rising edge; after it q==0 (the design
//     was already held at 0 by reset, so the first counted edge increments...
//     actually q goes 0 -> 1). We sample q AFTER the edge: cycle 0 prints the
//     value latched at that edge. With reset clearing q to 0 on the reset edge,
//     the first counted edge yields q=1. cycle n prints q == (n+1) & 0xFF.
// The downstream oracle only needs the literal text; the exact convention is
// documented so a re-implementation can reproduce identical lines.
`timescale 1ns/1ps
module counter_tb;
    reg        clk = 1'b0;
    reg        rst = 1'b1;
    wire [7:0] q;
    integer    cyc;

    counter dut (.clk(clk), .rst(rst), .q(q));

    initial begin
        $dumpfile("counter.ref.vcd");
        $dumpvars(0, counter_tb);

        // Hold reset across one full clock so the reset edge clears q.
        @(posedge clk);          // reset rising edge: q <= 0
        @(negedge clk);
        rst = 1'b0;              // release reset before next rising edge

        for (cyc = 0; cyc < 40; cyc = cyc + 1) begin
            @(posedge clk);      // counting edge
            #1;                  // settle nonblocking update before sampling
            $display("cycle %0d q=%0d", cyc, q);
        end
        $finish;
    end

    // free-running clock, 10ns period
    always #5 clk = ~clk;
endmodule

fpga/experiments/phase0/counter.ref.vcd
$date
	Wed Jun  3 11:59:07 2026
$end
$version
	Icarus Verilog
$end
$timescale
	1ps
$end
$scope module counter_tb $end
$var wire 8 ! q [7:0] $end
$var reg 1 " clk $end
$var reg 1 # rst $end
$var integer 32 $ cyc [31:0] $end
$scope module dut $end
$var wire 1 % _03_ $end
$var wire 1 & _04_ $end
$var wire 1 " clk $end
$var wire 1 # rst $end
$var wire 8 ' _02_ [7:0] $end
$var wire 8 ( _01_ [7:0] $end
$var wire 8 ) _00_ [7:0] $end
$var reg 8 * q [7:0] $end
$upscope $end
$upscope $end
$enddefinitions $end
$comment Show the parameter values. $end
$dumpall
$end
#0
$dumpvars
bx *
bzxxxxxxx )
bx (
bx '
x&
x%
bx $
1#
0"
bx !
$end
#5000
b1 '
0%
0&
bz0000000 )
b1 (
b0 !
b0 *
1"
#10000
b0 $
0#
0"
#15000
b0 (
b10 '
bz0000001 )
b1 !
b1 *
1"
#16000
b1 $
#20000
0"
#25000
b11 '
bz0000000 )
b11 (
b10 !
b10 *
1"
#26000
b10 $
#30000
0"
#35000
b10 (
b100 '
bz0000011 )
b11 !
b11 *
1"
#36000
b11 $
#40000
0"
#45000
b101 '
bz0000000 )
b101 (
b100 !
b100 *
1"
#46000
b100 $
#50000
0"
#55000
b100 (
b110 '
bz0000001 )
b101 !
b101 *
1"
#56000
b101 $
#60000
0"
#65000
b111 '
bz0000000 )
b111 (
b110 !
b110 *
1"
#66000
b110 $
#70000
0"
#75000
b110 (
b1000 '
bz0000111 )
b111 !
b111 *
1"
#76000
b111 $
#80000
0"
#85000
b1001 '
bz0000000 )
b1001 (
b1000 !
b1000 *
1"
#86000
b1000 $
#90000
0"
#95000
b1000 (
b1010 '
bz0000001 )
b1001 !
b1001 *
1"
#96000
b1001 $
#100000
0"
#105000
b1011 '
bz0000000 )
b1011 (
b1010 !
b1010 *
1"
#106000
b1010 $
#110000
0"
#115000
b1010 (
b1100 '
bz0000011 )
b1011 !
b1011 *
1"
#116000
b1011 $
#120000
0"
#125000
b1101 '
1%
bz0000000 )
b1101 (
b1100 !
b1100 *
1"
#126000
b1100 $
#130000
0"
#135000
b1100 (
b1110 '
bz0000001 )
b1101 !
b1101 *
1"
#136000
b1101 $
#140000
0"
#145000
b1111 '
bz0000000 )
b1111 (
b1110 !
b1110 *
1"
#146000
b1110 $
#150000
0"
#155000
b1110 (
b10000 '
bz0001111 )
b1111 !
b1111 *
1"
#156000
b1111 $
#160000
0"
#165000
0%
b10001 '
bz0000000 )
b10001 (
b10000 !
b10000 *
1"
#166000
b10000 $
#170000
0"
#175000
b10000 (
b10010 '
bz0000001 )
b10001 !
b10001 *
1"
#176000
b10001 $
#180000
0"
#185000
b10011 '
bz0000000 )
b10011 (
b10010 !
b10010 *
1"
#186000
b10010 $
#190000
0"
#195000
b10010 (
b10100 '
bz0000011 )
b10011 !
b10011 *
1"
#196000
b10011 $
#200000
0"
#205000
b10101 '
bz0000000 )
b10101 (
b10100 !
b10100 *
1"
#206000
b10100 $
#210000
0"
#215000
b10100 (
b10110 '
bz0000001 )
b10101 !
b10101 *
1"
#216000
b10101 $
#220000
0"
#225000
b10111 '
bz0000000 )
b10111 (
b10110 !
b10110 *
1"
#226000
b10110 $
#230000
0"
#235000
b10110 (
b11000 '
bz0000111 )
b10111 !
b10111 *
1"
#236000
b10111 $
#240000
0"
#245000
b11001 '
bz0000000 )
b11001 (
b11000 !
b11000 *
1"
#246000
b11000 $
#250000
0"
#255000
b11000 (
b11010 '
bz0000001 )
b11001 !
b11001 *
1"
#256000
b11001 $
#260000
0"
#265000
b11011 '
bz0000000 )
b11011 (
b11010 !
b11010 *
1"
#266000
b11010 $
#270000
0"
#275000
b11010 (
b11100 '
bz0000011 )
b11011 !
b11011 *
1"
#276000
b11011 $
#280000
0"
#285000
b11101 '
1%
bz0000000 )
b11101 (
b11100 !
b11100 *
1"
#286000
b11100 $
#290000
0"
#295000
b11100 (
b11110 '
bz0000001 )
b11101 !
b11101 *
1"
#296000
b11101 $
#300000
0"
#305000
b11111 '
bz0000000 )
b11111 (
b11110 !
b11110 *
1"
#306000
b11110 $
#310000
0"
#315000
b11110 (
b100000 '
bz0011111 )
b11111 !
b11111 *
1"
#316000
b11111 $
#320000
0"
#325000
0%
b100001 '
bz0000000 )
b100001 (
b100000 !
b100000 *
1"
#326000
b100000 $
#330000
0"
#335000
b100000 (
b100010 '
bz0000001 )
b100001 !
b100001 *
1"
#336000
b100001 $
#340000
0"
#345000
b100011 '
bz0000000 )
b100011 (
b100010 !
b100010 *
1"
#346000
b100010 $
#350000
0"
#355000
b100010 (
b100100 '
bz0000011 )
b100011 !
b100011 *
1"
#356000
b100011 $
#360000
0"
#365000
b100101 '
bz0000000 )
b100101 (
b100100 !
b100100 *
1"
#366000
b100100 $
#370000
0"
#375000
b100100 (
b100110 '
bz0000001 )
b100101 !
b100101 *
1"
#376000
b100101 $
#380000
0"
#385000
b100111 '
bz0000000 )
b100111 (
b100110 !
b100110 *
1"
#386000
b100110 $
#390000
0"
#395000
b100110 (
b101000 '
bz0000111 )
b100111 !
b100111 *
1"
#396000
b100111 $
#400000
0"
#405000
b101001 '
bz0000000 )
b101001 (
b101000 !
b101000 *
1"
#406000
b101000 $
